main.py
rembrandt_cli-0.0.0.dist-info/METADATA
rembrandt_cli-0.0.0.dist-info/WHEEL
rembrandt_cli-0.0.0.dist-info/top_level.txt
rembrandt_cli-0.0.0.dist-info/RECORD
