Metadata-Version: 2.1
Name: rembrandt-cli
Version: 0.0.0
Summary: cryptic game client and library
Home-page: https://github.com/GecraftetHD/rembrandt_cli
Author: Gecraftet_hd
Author-email: 
License: UNKNOWN
Platform: UNKNOWN
